izihawa_nlptools-1.2.0.dist-info/METADATA
izihawa_nlptools-1.2.0.dist-info/RECORD
izihawa_nlptools-1.2.0.dist-info/WHEEL
izihawa_nlptools/__init__.py
izihawa_nlptools/language_detect.py
izihawa_nlptools/morph.py
izihawa_nlptools/regex.py
izihawa_nlptools/utils.py
models/lid.176.ftz
