Metadata-Version: 2.1
Name: izihawa-nlptools
Version: 1.2.0
Author: Pasha Podolsky
Author-email: ppodolsky@me.com
Home-page: https://github.com/izihawa/nlptools
License: MIT License
Classifier: Topic :: Utilities
Classifier: Programming Language :: Python :: 3.8
Requires-Python: >=3.8
Requires-Dist: emoji < 2
Requires-Dist: lemminflect >= 0.2.2
Requires-Dist: fasttext >= 0.9.2
Requires-Dist: spacy >= 3.3.0
Requires-Dist: pymorphy2 >= 0.9.1
